hsmap/__init__.py
hsmap/config.py
hsmap/filter.py
hsmap/timeutil.py
hsmap/utils.py
hsmap-0.1.6.dist-info/LICENSE
hsmap-0.1.6.dist-info/WHEEL
hsmap-0.1.6.dist-info/METADATA
hsmap-0.1.6.dist-info/RECORD
